grasping_position_inference/__init__.py
grasping_position_inference/root.py
grasping_position_inference/inference/__init__.py
grasping_position_inference/inference/grid.py
grasping_position_inference/inference/model.py
grasping_position_inference/inference/predicator.py
grasping_position_inference/inference/probability_grid.py
grasping_position_inference/test/__init__.py
grasping_position_inference/test/inference/__init__.py
grasping_position_inference/test/inference/grid_test.py
grasping_position_inference/test/inference/predicator_test.py
grasping_position_inference/test/inference/probability_grid_test.py
grasping_position_inference/test/training/__init__.py
grasping_position_inference/test/training/model_generator.py
grasping_position_inference/test/training/model_test.py
grasping_position_inference/training/__init__.py
grasping_position_inference/training/exceptions.py
grasping_position_inference/training/model.py
grasping_position_inference/training/model_generator.py
grasping_position_inference-1.1.0.dist-info/LICENSE
grasping_position_inference-1.1.0.dist-info/METADATA
grasping_position_inference-1.1.0.dist-info/WHEEL
grasping_position_inference-1.1.0.dist-info/top_level.txt
grasping_position_inference-1.1.0.dist-info/RECORD
