Metadata-Version: 2.1
Name: grasping-position-inference
Version: 1.1.0
Summary: Utilizes machine learning to infer the most probable grasping position for a defined object
Home-page: https://github.com/code-iai/grasping_location_inference
Author: Sebastian Koralewski
Author-email: seba@cs.uni-bremen.de
License: UNKNOWN
Platform: UNKNOWN
Classifier: Programming Language :: Python :: 2
Classifier: License :: OSI Approved :: MIT License
Classifier: Operating System :: OS Independent
Requires-Dist: numpy (==1.14.2)
Requires-Dist: scikit-learn (==0.20.0)
